[
    {
        "SKU": "ESNL93226A420",
        "ListedSKU": "WC153968",
        "ParentSKU": null,
        "Category": "Jewellery",
        "EAN": "4891945215248",
        "Title": "Esprit Silver Symphony Silver",
        "Description": "Esprit Silver Symphony Silver",
        "Brand": "Esprit Silver",
        "RRP": 99.9,
        "Price": 58.45,
        "PriceUpdateUTC": null,
        "Stock": 7,
        "StockUpdateUTC": "2018-10-11T22:46:56.683",
        "SPEC_Model_Name": "Symphony",
        "SPEC_Target_audience": "Women",
        "SPEC_Weight-Gram": "5.7",
        "SPEC_Jewel_type": "Necklace",
        "SPEC_Metal_type": "925 Sterling Silver",
        "SPEC_Metal Color": "Silver",
        "SPEC_Clasp_type": "Lobster claw clasp",
        "SPEC_Height-cm": "1.8",
        "SPEC_Length-cm": "42",
        "SPEC_Width-cm": "0.9",
        "SPEC_Gem_shape": "Round",
        "SPEC_Gem_type": "Cubic Zirkonia",
        "SPEC_Gem_color": "White",
        "SPEC_Gem_quantity": "9",
        "SPEC_Fruugo Title": "Esprit Silver Symphony Silver ESNL93226",
        "SPEC_Fruugo Description": "Esprit Silver Symphony Silver ESNL93226A420",
        "SPEC_Fruugo Category": "Apparel & Accessories > Jewelry > Necklaces > Womens",
        "Images": [
            {
                "ImageSort": null,
                "ImageURL": "https://uwt.blob.core.windows.net/dsales/partimage/esnl93226a420_rwy7a4.jpg",
                "IsDefault": true,
                "ImageUpdateUTC": "2017-04-20T08:37:57"
            },
            {
                "ImageSort": null,
                "ImageURL": "https://uwt.blob.core.windows.net/dsales/partimage/esnl93226a420_8ubdba.jpg",
                "ImageUpdateUTC": "2017-05-29T14:20:19"
            },
            {
                "ImageSort": 1,
                "ImageURL": "https://uwt.blob.core.windows.net/dsales/partimage/esnl93226a420_576l94.jpg",
                "ImageUpdateUTC": "2017-05-10T13:52:27"
            },
            {
                "ImageSort": 3,
                "ImageURL": "https://uwt.blob.core.windows.net/dsales/partimage/esnl93226a420_lksfyl.jpg",
                "ImageUpdateUTC": "2017-05-10T13:52:27"
            },
            {
                "ImageSort": 4,
                "ImageURL": "https://uwt.blob.core.windows.net/dsales/partimage/esnl93226a420_axkfod.jpg",
                "ImageUpdateUTC": "2017-05-10T13:52:27"
            }
        ]
    },
    {
        "SKU": "OR51707",
        "ListedSKU": "WC162248",
        "ParentSKU": null,
        "Category": "Watches",
        "EAN": "5415190082173",
        "Title": "ORPHELIA Unisex Analogue Watch Suede Burgundy Leather",
        "Description": "ORPHELIA Unisex Analogue Watch Suede Burgundy Leather",
        "Brand": "ORPHELIA",
        "RRP": 89,
        "Price": 89,
        "PriceUpdateUTC": null,
        "Stock": 2,
        "StockUpdateUTC": "2018-10-11T22:55:55.937",
        "SPEC_FNSKU": "X000S3U68X",
        "SPEC_Model Name": "Suede",
        "SPEC_Target_Audience": "Unisex",
        "SPEC_Display_Type": "Analogue",
        "SPEC_Movement": "Quartz",
        "SPEC_Features_1": "Luminous Hand",
        "SPEC_ATM": "3 bars",
        "SPEC_Case_material": "Alloy",
        "SPEC_Case_Style": "Round",
        "SPEC_Case_color": "Rose gold",
        "SPEC_Dial_Color": "Burgundy",
        "SPEC_Band_Material": "Leather",
        "SPEC_Band_Color": "Burgundy",
        "SPEC_Band_Width_mm": "20",
        "SPEC_Band_Length_cm": "21",
        "SPEC_Case_Diameter_mm": "40",
        "SPEC_Case_Thickness_mm": "9",
        "SPEC_Clasp_Type": "Buckle",
        "SPEC_Weight_g": "80",
        "SPEC_Dial_Window_Material": "Mineral Glas",
        "SPEC_Battery": "377",
        "SPEC_Product Description": "Orphelia",
        "SPEC_Brand Description": "Orphelia was established in Belgium in 1996, it offers a wide collection of watches and jewellery for men and women.  Pure and original designs that suit all tastes and can be worn on all occasions.  Classic, sleek, urban, romantic, contemporary, sporty and fashion styles that are distinguished by their styles, designs and high quality.  The Orphelia brand promises classic luxury Jewels and Watches that focuses on details.",
        "SPEC_Catalogue": "Yes",
        "SPEC_Catalogue Year": "2018",
        "SPEC_Fruugo Title": "ORPHELIA Unisex Analogue Watch Suede Burgundy Leather OR51707",
        "SPEC_Fruugo Description": "ORPHELIA Unisex Analogue Watch Suede Burgundy Leather OR51707",
        "SPEC_Fruugo Category": "Apparel & Accessories > Jewelry > Watches > Adult (unisex)",
        "Images": [
            {
                "ImageSort": null,
                "ImageURL": "https://uwt.blob.core.windows.net/dsales/partimage/uvtajja9_51707.jpg",
                "IsDefault": true,
                "ImageUpdateUTC": "2017-11-21T16:34:01"
            },
            {
                "ImageSort": 1,
                "ImageURL": "https://uwt.blob.core.windows.net/dsales/partimage/h8jcb6vm_51707.jpg",
                "ImageUpdateUTC": "2018-05-29T14:28:05"
            },
            {
                "ImageSort": 3,
                "ImageURL": "https://uwt.blob.core.windows.net/dsales/partimage/pyy4n229_or51707.jpg",
                "ImageUpdateUTC": "2018-05-29T14:28:05"
            },
            {
                "ImageSort": 4,
                "ImageURL": "https://uwt.blob.core.windows.net/dsales/partimage/gvezjqdj_or51707.jpg",
                "ImageUpdateUTC": "2018-05-29T14:28:05"
            },
            {
                "ImageSort": 5,
                "ImageURL": "https://uwt.blob.core.windows.net/dsales/partimage/xmw24uv5_or51707.jpg",
                "ImageUpdateUTC": "2018-05-29T14:28:05"
            },
            {
                "ImageSort": 6,
                "ImageURL": "https://uwt.blob.core.windows.net/dsales/partimage/i4dxqva5_51707.jpg",
                "ImageUpdateUTC": "2018-05-29T14:28:05"
            },
            {
                "ImageSort": 7,
                "ImageURL": "https://uwt.blob.core.windows.net/dsales/partimage/fefah3xd_51707.jpg",
                "ImageUpdateUTC": "2018-05-29T14:28:05"
            }
        ]
    },
    {
        "SKU": "OR51706",
        "ListedSKU": "WC162285",
        "ParentSKU": null,
        "Category": "Watches",
        "EAN": "5415190082166",
        "Title": "ORPHELIA Unisex Analogue Watch Suede Green Leather",
        "Description": "ORPHELIA Unisex Analogue Watch Suede Green Leather",
        "Brand": "ORPHELIA",
        "RRP": 89,
        "Price": 89,
        "PriceUpdateUTC": null,
        "Stock": 7,
        "StockUpdateUTC": "2018-10-11T22:55:55.937",
        "SPEC_FNSKU": "X000S3QGO1",
        "SPEC_Model Name": "Suede",
        "SPEC_Target_Audience": "Unisex",
        "SPEC_Display_Type": "Analogue",
        "SPEC_Movement": "Quartz",
        "SPEC_Features_1": "Luminous Hand",
        "SPEC_Calendar": "Date",
        "SPEC_ATM": "3 bars",
        "SPEC_Case_material": "Alloy",
        "SPEC_Case_Style": "Round",
        "SPEC_Case_color": "Rose gold",
        "SPEC_Dial_Color": "Green",
        "SPEC_Band_Material": "Leather",
        "SPEC_Band_Color": "Brown",
        "SPEC_Band_Width_mm": "20",
        "SPEC_Band_Length_cm": "21",
        "SPEC_Case_Diameter_mm": "40",
        "SPEC_Case_Thickness_mm": "9",
        "SPEC_Clasp_Type": "Buckle",
        "SPEC_Weight_g": "80",
        "SPEC_Dial_Window_Material": "Mineral Glas",
        "SPEC_Battery": "377",
        "SPEC_Product Description": "Orphelia",
        "SPEC_Brand Description": "Orphelia was established in Belgium in 1996, it offers a wide collection of watches and jewellery for men and women.  Pure and original designs that suit all tastes and can be worn on all occasions.  Classic, sleek, urban, romantic, contemporary, sporty and fashion styles that are distinguished by their styles, designs and high quality.  The Orphelia brand promises classic luxury Jewels and Watches that focuses on details.",
        "SPEC_Catalogue": "Yes",
        "SPEC_Catalogue Year": "2018",
        "SPEC_Fruugo Title": "ORPHELIA Unisex Analogue Watch Suede Green Leather OR51706",
        "SPEC_Fruugo Description": "ORPHELIA Unisex Analogue Watch Suede Green Leather OR51706",
        "SPEC_Fruugo Category": "Apparel & Accessories > Jewelry > Watches > Adult (unisex)",
        "Images": [
            {
                "ImageSort": 1,
                "ImageURL": "https://uwt.blob.core.windows.net/dsales/partimage/zczkv7d1_51706.jpg",
                "IsDefault": true,
                "ImageUpdateUTC": "2017-11-22T10:00:54"
            },
            {
                "ImageSort": 1,
                "ImageURL": "https://uwt.blob.core.windows.net/dsales/partimage/u68d5vec_51706.jpg",
                "ImageUpdateUTC": "2018-05-28T14:34:04"
            },
            {
                "ImageSort": 2,
                "ImageURL": "https://uwt.blob.core.windows.net/dsales/partimage/926y4u8b_or51706.jpg",
                "ImageUpdateUTC": "2018-05-28T14:34:04"
            },
            {
                "ImageSort": 4,
                "ImageURL": "https://uwt.blob.core.windows.net/dsales/partimage/2cewyn2x_or51706.jpg",
                "ImageUpdateUTC": "2018-05-28T14:34:04"
            },
            {
                "ImageSort": 6,
                "ImageURL": "https://uwt.blob.core.windows.net/dsales/partimage/2xyjiyi5_51706.jpg",
                "ImageUpdateUTC": "2018-05-28T14:34:04"
            },
            {
                "ImageSort": 7,
                "ImageURL": "https://uwt.blob.core.windows.net/dsales/partimage/bunrxwao_51706.jpg",
                "ImageUpdateUTC": "2018-05-28T14:34:04"
            }
        ]
    },
    {
        "SKU": "OR51705",
        "ListedSKU": "WC162310",
        "ParentSKU": null,
        "Category": "Watches",
        "EAN": "5415190082159",
        "Title": "ORPHELIA Unisex Analogue Watch Suede Blue Leather",
        "Description": "ORPHELIA Unisex Analogue Watch Suede Blue Leather",
        "Brand": "ORPHELIA",
        "RRP": 89,
        "Price": 89,
        "PriceUpdateUTC": null,
        "Stock": 7,
        "StockUpdateUTC": "2018-10-11T22:55:55.937",
        "SPEC_FNSKU": "X000S3QGKP",
        "SPEC_Model Name": "Suede",
        "SPEC_Target_Audience": "Unisex",
        "SPEC_Display_Type": "Analogue",
        "SPEC_Movement": "Quartz",
        "SPEC_Features_1": "Luminous Hand",
        "SPEC_Calendar": "Date",
        "SPEC_ATM": "3 bars",
        "SPEC_Case_material": "Alloy",
        "SPEC_Case_Style": "Round",
        "SPEC_Case_color": "Rose gold",
        "SPEC_Dial_Color": "Blue",
        "SPEC_Band_Material": "Leather",
        "SPEC_Band_Color": "Blue",
        "SPEC_Band_Width_mm": "20",
        "SPEC_Band_Length_cm": "21",
        "SPEC_Case_Diameter_mm": "40",
        "SPEC_Case_Thickness_mm": "9",
        "SPEC_Clasp_Type": "Buckle",
        "SPEC_Weight_g": "80",
        "SPEC_Dial_Window_Material": "Mineral Glas",
        "SPEC_Battery": "377",
        "SPEC_Product Description": "Orphelia",
        "SPEC_Brand Description": "Orphelia was established in Belgium in 1996, it offers a wide collection of watches and jewellery for men and women.  Pure and original designs that suit all tastes and can be worn on all occasions.  Classic, sleek, urban, romantic, contemporary, sporty and fashion styles that are distinguished by their styles, designs and high quality.  The Orphelia brand promises classic luxury Jewels and Watches that focuses on details.",
        "SPEC_Catalogue": "Yes",
        "SPEC_Catalogue Year": "2018",
        "SPEC_Fruugo Title": "ORPHELIA Unisex Analogue Watch Suede Blue Leather OR51705",
        "SPEC_Fruugo Description": "ORPHELIA Unisex Analogue Watch Suede Blue Leather OR51705",
        "SPEC_Fruugo Category": "Apparel & Accessories > Jewelry > Watches > Adult (unisex)",
        "Images": [
            {
                "ImageSort": null,
                "ImageURL": "https://uwt.blob.core.windows.net/dsales/partimage/75pl9oc2_51705.jpg",
                "IsDefault": true,
                "ImageUpdateUTC": "2017-11-21T16:34:01"
            },
            {
                "ImageSort": 1,
                "ImageURL": "https://uwt.blob.core.windows.net/dsales/partimage/p25lmta3_51705.jpg",
                "ImageUpdateUTC": "2018-07-03T11:15:10"
            },
            {
                "ImageSort": 2,
                "ImageURL": "https://uwt.blob.core.windows.net/dsales/partimage/sis9sacz_or51705.jpg",
                "ImageUpdateUTC": "2018-07-03T11:15:10"
            },
            {
                "ImageSort": 3,
                "ImageURL": "https://uwt.blob.core.windows.net/dsales/partimage/e45b87pl_or51705.jpg",
                "ImageUpdateUTC": "2018-07-03T11:15:10"
            },
            {
                "ImageSort": 4,
                "ImageURL": "https://uwt.blob.core.windows.net/dsales/partimage/8j58yino_or51705.jpg",
                "ImageUpdateUTC": "2018-07-03T11:15:10"
            },
            {
                "ImageSort": 5,
                "ImageURL": "https://uwt.blob.core.windows.net/dsales/partimage/bpsm8ddd_51705.jpg",
                "ImageUpdateUTC": "2018-07-03T11:15:10"
            },
            {
                "ImageSort": 6,
                "ImageURL": "https://uwt.blob.core.windows.net/dsales/partimage/bktgrpb9_51705.jpg",
                "ImageUpdateUTC": "2018-07-03T11:15:10"
            }
        ]
    },
    {
        "SKU": "ZR-7097/56",
        "ListedSKU": "WC152920",
        "ParentSKU": "ZR-7097",
        "Category": "Jewellery",
        "EAN": "5415190040241",
        "Title": "Orphelia Silver 925 Ring Two Layered Glitter",
        "Description": "Orphelia Silver 925 Ring Two Layered Glitter",
        "Brand": "ORPHELIA SILVER",
        "RRP": 79,
        "Price": 46.62,
        "PriceUpdateUTC": null,
        "Stock": 1,
        "StockUpdateUTC": "2018-10-11T22:40:09.667",
        "SPEC_Target_audience": "Women",
        "SPEC_Jewel_type": "Ring",
        "SPEC_Metal_type": "925 Sterling Silver",
        "SPEC_Metal Color": "Silver",
        "SPEC_Ring_size": "56",
        "SPEC_Ring type": "Ring without stones",
        "SPEC_Fruugo Title": "Ring Two Layered Glitter ZR-7097",
        "SPEC_Fruugo Description": "Ring Two Layered Glitter ZR-7097/56",
        "SPEC_Fruugo Category": "Jewellery > Women > Ring",
        "Images": [
            {
                "ImageSort": null,
                "ImageURL": "https://uwt.blob.core.windows.net/dsales/partimage/zr-709756_o160dh.jpg",
                "IsDefault": true,
                "ImageUpdateUTC": "2016-04-13T15:08:55"
            },
            {
                "ImageSort": null,
                "ImageURL": "https://uwt.blob.core.windows.net/dsales/partimage/zr-709756_07rt3v.jpg",
                "ImageUpdateUTC": "2016-04-13T15:08:56"
            },
            {
                "ImageSort": null,
                "ImageURL": "https://uwt.blob.core.windows.net/dsales/partimage/zr-709756_0m67yf.jpg",
                "ImageUpdateUTC": "2016-04-13T15:08:58"
            },
            {
                "ImageSort": null,
                "ImageURL": "https://uwt.blob.core.windows.net/dsales/partimage/zr-709756_4w9wr1.jpg",
                "ImageUpdateUTC": "2017-09-12T13:04:06"
            }
        ]
    }
]